aiorem/__about__.py
aiorem/__init__.py
aiorem/_resourcemanager.py
aiorem/_resourcemanagercollection.py
aiorem/py.typed
aiorem-0.0.1.dist-info/METADATA
aiorem-0.0.1.dist-info/WHEEL
aiorem-0.0.1.dist-info/licenses/LICENSE.txt
aiorem-0.0.1.dist-info/RECORD
