Metadata-Version: 2.3
Name: aiorem
Version: 0.0.1
Summary: asyncio Context Manager with Explicit Interface
Project-URL: Documentation, https://aiorem.readthedocs.io/
Project-URL: Issues, https://github.com/Bibo-Joshi/aiorem/issues
Project-URL: Source, https://github.com/Bibo-Joshi/aiorem
Author-email: Hinrich Mahler <aiorem@mahlerhome.de>
License-Expression: MIT
License-File: LICENSE.txt
Keywords: asyncio,contextmanager,resources
Classifier: Development Status :: 4 - Beta
Classifier: Intended Audience :: Developers
Classifier: Operating System :: OS Independent
Classifier: Programming Language :: Python
Classifier: Programming Language :: Python :: 3.11
Classifier: Programming Language :: Python :: 3.12
Classifier: Topic :: Software Development :: Libraries :: Python Modules
Requires-Python: >=3.11
